{"videoinfo":{"0":{"0":"Big Titty Ava Lauren Brunette Deep Throats And Gets Fucked Doggy Style","1":"689492"},"1":{"0":"BLACKEDRAW Ava Addams Is Fucking BBC And Sending Pics To Her Husband","1":"36971335"},"2":{"0":"BANGBROS - Big Tit MILF Ava Addams Gets Anal Slammed By Mike Adriano","1":"47557973"},"3":{"0":"Ava Adams POV","1":"924758"},"4":{"0":"Ava Addams Cumshot Compilation","1":"38696189"},"5":{"0":"Ava Addams, milf sexy aime la bite de Manuel Ferrara","1":"46961629"},"6":{"0":"Ava Adams","1":"4381766"},"7":{"0":"Brazzers - Ava Addams - Doctor Adventures","1":"27057359"},"8":{"0":"Mommy Got Boobs - (Ava Addams, Ricky Johnson) - Seduced By His Stepmom - Brazzers","1":"49552457"},"9":{"0":"Milfs Like it Big - (Ava Addams, Keiran Lee) - Red Carpet Streaker - Brazzers","1":"54249515"},"10":{"0":"Jules Jordan - Big tit MILF Ava Addams is a Bra Buster!","1":"46625701"},"11":{"0":"Ava Addams me r&eacute;veille avec ses gros seins","1":"53370279"},"12":{"0":"PureMature - Ava Addams and her gigantic tits fucked","1":"24294415"},"13":{"0":"Ava Addams RARE Homemade Sex Scene","1":"51618065"},"14":{"0":"BANGBROS - Mae Olsen Walks In On Her Boyfriend Cheating With The Maid, Ava Addams","1":"46286809"},"15":{"0":"Petite stepsister pov blows stepbrother","1":"8242146"},"16":{"0":"Axxxteca: Lucky mexican dancer gets to fuck Ava Addams and he squeezes her huge tits!!","1":"51955117"},"17":{"0":"Mom bates step son","1":"48744475"},"18":{"0":"MILF SUPERSTAR AVA ADDAMS FUCKED HARD IN A HOTEL ROOM","1":"53451327"},"19":{"0":"Ava fucked her personal trainer Erik","1":"14553593"},"20":{"0":"Brazzers - Ava Addams - Big Tits at Work","1":"26966485"},"21":{"0":"Brazzers - step Mommy Got Boobs - Stay Away From My step Daughter scene starring Ava Addams and Keiran Lee","1":"30077289"},"22":{"0":"PUREMATURE Busty mature Ava Addams interrupts phone call for fuck","1":"27389207"},"23":{"0":"Ava Addams, milf aux seins &eacute;normes veut une bonne baise","1":"49906965"},"24":{"0":"Ava courcelles","1":"54435571"},"25":{"0":"Brazzers - Moms in control - Squeaky Clean scene starring Ava Addams Megan Rain and Jordi El Ni&amp;","1":"29996309"},"26":{"0":"Hardcore Sex With Naughty Busty Sexy Wife (Ava Addams) video-06","1":"27502435"},"27":{"0":"madrastra cachonda","1":"61101833"},"28":{"0":"Ava Addams and her big tits suck 3 cocks at gloryhole","1":"71146823"},"29":{"0":"FILTHY FAMILY - Think You Can Handle Ava Addams, Son? That&#039;s A Lot Of Woman.","1":"69185731"},"30":{"0":"Ava Addams Big Tits HD","1":"12726145"},"31":{"0":"Hot big boob milf takes on Bruce Venture&#039;s giant Dick!","1":"56807025"},"32":{"0":"Ultimate Horny Stepmom Ava Addams Catches Stepson Sniffing her Panties and gets Mad","1":"48751517"},"33":{"0":"Hot Step Mom- Ava Adams","1":"17252667"},"34":{"0":"Ava Addams got her anal drilled so deep by Bill Bailey","1":"25880561"},"35":{"0":"Gigantic boobs MILF catches panty thief and fucks him","1":"30189483"},"36":{"0":"Ava Adams Double Pentration ByTwo Guys","1":"28701997"},"37":{"0":"BANGBROS - Battle Of The GOATs: Ava Addams VS Bridgette B","1":"64258371"},"38":{"0":"Busty milf Ava Addams fuck a large dick","1":"11919955"},"39":{"0":"my wife for yours","1":"23860924"},"40":{"0":"Sara jay and devine","1":"10939301"},"41":{"0":"step Mom and Her Jealous Virgin Son","1":"37473101"},"42":{"0":"Huge tits MILF Ava Addams sucks and fucks a dude","1":"17976577"},"43":{"0":"rws ava addams bb021314 720p 3800","1":"17090747"},"44":{"0":"Big Titted Fuck Goddess Ava Addams Squirts On A Big White Cock","1":"9428182"},"45":{"0":"Succubi Lisa Ann and Ava Addams 3way banged before facial","1":"48993791"},"46":{"0":"La milf Ava se masturba para mi","1":"69843601"},"47":{"0":"Sexy Busty Wife (Ava Addams) Love Intercorse On Camera movie-05","1":"26795137"},"48":{"0":"Bigtits MILF Ava Addams fucking a young guy","1":"19441581"},"49":{"0":"Ava Addams vs. Jon Jon (Hot Fuck Scene!)","1":"9363755"},"50":{"0":"Milf with HUGE tits fucked hard - milf porn","1":"51426459"},"51":{"0":"Busty MILF Ava Addams used by lesbian massage professional Cherie DeVille","1":"71202521"},"52":{"0":"Busty milf butthole licked after anal fucking","1":"64683975"},"53":{"0":"How Many Nuts can she Bust","1":"23513694"},"54":{"0":"MILF With Huge Tits Gets Fucked","1":"289829"},"55":{"0":"Ava Addams Uses Her Massive Tits On Cock","1":"39634173"},"56":{"0":"Naughty America - Ava Addams comes home with new Lingerie","1":"50823087"},"57":{"0":"Ava Addams Busty Milf Gets Fucked","1":"18753227"},"58":{"0":"BLACKED MILF only fucks BBC","1":"42177123"},"59":{"0":"Jayden Jaymes and Ava Addams threesome fucking","1":"61163317"},"60":{"0":"BANGBROS - Big Titty MILF Ava Addams Gets Anal Slammed By Mike Adriano","1":"38585225"},"61":{"0":"Pure Mature MILF&#039;s massive tits fucked by a big dick","1":"8487031"},"62":{"0":"Bigass pussy assfuck","1":"6775226"},"63":{"0":"Penetrating Sexy Pussy!","1":"42776027"},"64":{"0":"BANGBROS - Jada Stevens, Ava Addams, &amp; Christy Mack Demolish College Dorm","1":"34126051"},"65":{"0":"FILTHY FAMILY - Awesomesauce Compilation Featuring Julianna Vega, Diamond Kitty, Ava Addams &amp; More","1":"63971107"},"66":{"0":"Sexy MILF in Maid Outfit","1":"23895020"},"67":{"0":"Ava Addams Fucks Daughter&#039;s BF","1":"47582733"},"68":{"0":"Huge Tits Pornstar Makes Her Stalker&#039;s Dreams Come True - Ava Addams","1":"63180979"},"69":{"0":"HD - FantasyHD Ava Addams huge tits gets cum blasted","1":"10069123"},"70":{"0":"Ava Devine With A pizza delivery boy","1":"10858001"},"71":{"0":"Eriks balls was inside Avas pretty mouth","1":"14572691"},"72":{"0":"Black ex GF with huge booty rides cock","1":"2318020"},"73":{"0":"Spex teen rough fingered","1":"15216481"},"74":{"0":"Ava Kelly swallows cum after being throat fucked","1":"7476799"},"75":{"0":"Tempting maiden Ava Sparxxx gets huge dangler into her muff","1":"54588171"},"76":{"0":"New fuck-session from mature real married webcam couple...","1":"71291273"},"77":{"0":"18 years teen evaava  masturbate pussy and fuck tight asshole with anal plug till get an orgasm","1":"68148207"},"78":{"0":"Teen ava Taylors first porn scene","1":"7039994"},"79":{"0":"bb","1":"1562041"},"80":{"0":"3 girls on black cock","1":"1066935"}},"link":{"0":{"0":"https:\/\/porn.yamyhub.com\/video\/reagan-foxx\/","1":"reagan foxx"},"1":{"0":"https:\/\/porn.yamyhub.com\/video\/eliza-ibarra\/","1":"eliza ibarra"},"2":{"0":"https:\/\/porn.yamyhub.com\/video\/christie-stevens\/","1":"christie stevens"},"3":{"0":"https:\/\/porn.yamyhub.com\/video\/lena-paul\/","1":"lena paul"},"4":{"0":"https:\/\/porn.yamyhub.com\/video\/sara-jay\/","1":"sara jay"},"5":{"0":"https:\/\/porn.yamyhub.com\/video\/kendra-lust\/","1":"kendra lust"},"6":{"0":"https:\/\/porn.yamyhub.com\/video\/mia-malkova\/","1":"mia malkova"},"7":{"0":"https:\/\/porn.yamyhub.com\/video\/gia-derza\/","1":"gia derza"},"8":{"0":"https:\/\/porn.yamyhub.com\/video\/dee-williams\/","1":"dee williams"},"9":{"0":"https:\/\/porn.yamyhub.com\/video\/alina-lopez\/","1":"alina lopez"},"10":{"0":"https:\/\/porn.yamyhub.com\/video\/alex-adams\/","1":"alex adams"},"11":{"0":"https:\/\/porn.yamyhub.com\/video\/chanel-preston\/","1":"chanel preston"}}}